safexl/__init__.py
safexl/colors.py
safexl/toolkit.py
safexl/xl_constants.py
safexl/tests/__init__.py
safexl/tests/test_app.py
safexl/tests/test_app_tools.py
safexl/tests/test_psutil_wrappers.py
safexl-0.0.7.dist-info/LICENCE.rst
safexl-0.0.7.dist-info/METADATA
safexl-0.0.7.dist-info/WHEEL
safexl-0.0.7.dist-info/top_level.txt
safexl-0.0.7.dist-info/RECORD
