Metadata-Version: 2.1
Name: safexl
Version: 0.0.7
Summary: The Safe Way to Excel
Home-page: https://github.com/ThePoetCoder/safexl
Author: Eric Smith
Author-email: ThePoetCoder@gmail.com
License: MIT
Keywords: safexl Excel pywin32 win32 spreadsheet
Platform: UNKNOWN
Classifier: Development Status :: 4 - Beta
Classifier: Intended Audience :: Developers
Classifier: License :: OSI Approved :: MIT License
Classifier: Natural Language :: English
Classifier: Operating System :: Microsoft :: Windows
Classifier: Topic :: Office/Business :: Financial :: Spreadsheet
Classifier: Programming Language :: Python
Classifier: Programming Language :: Python :: 3.6
Classifier: Programming Language :: Python :: 3.7
Classifier: Programming Language :: Python :: 3.8
Requires-Python: >=3.6
Requires-Dist: pywin32 (>=223)
Requires-Dist: psutil (>=5.6.2)
